NiukeYouxiCehuaGangQiuzhiJingyanFenxiang20212022Fix1/README.md
NiukeYouxiCehuaGangQiuzhiJingyanFenxiang20212022Fix1/__init__.py
NiukeYouxiCehuaGangQiuzhiJingyanFenxiang20212022Fix1/__main__.py
NiukeYouxiCehuaGangQiuzhiJingyanFenxiang20212022Fix1/file.epub
NiukeYouxiCehuaGangQiuzhiJingyanFenxiang20212022Fix1/index.html
NiukeYouxiCehuaGangQiuzhiJingyanFenxiang20212022Fix1/css/__init__.py
NiukeYouxiCehuaGangQiuzhiJingyanFenxiang20212022Fix1/css/annotations.css
NiukeYouxiCehuaGangQiuzhiJingyanFenxiang20212022Fix1/css/main.css
NiukeYouxiCehuaGangQiuzhiJingyanFenxiang20212022Fix1/css/normalize.css
NiukeYouxiCehuaGangQiuzhiJingyanFenxiang20212022Fix1/css/popup.css
NiukeYouxiCehuaGangQiuzhiJingyanFenxiang20212022Fix1/font/__init__.py
NiukeYouxiCehuaGangQiuzhiJingyanFenxiang20212022Fix1/font/fontello.eot
NiukeYouxiCehuaGangQiuzhiJingyanFenxiang20212022Fix1/font/fontello.svg
NiukeYouxiCehuaGangQiuzhiJingyanFenxiang20212022Fix1/font/fontello.ttf
NiukeYouxiCehuaGangQiuzhiJingyanFenxiang20212022Fix1/font/fontello.woff
NiukeYouxiCehuaGangQiuzhiJingyanFenxiang20212022Fix1/img/__init__.py
NiukeYouxiCehuaGangQiuzhiJingyanFenxiang20212022Fix1/img/annotator-glyph-sprite.png
NiukeYouxiCehuaGangQiuzhiJingyanFenxiang20212022Fix1/img/annotator-icon-sprite.png
NiukeYouxiCehuaGangQiuzhiJingyanFenxiang20212022Fix1/img/apple-touch-icon.png
NiukeYouxiCehuaGangQiuzhiJingyanFenxiang20212022Fix1/img/cancelfullscreen.png
NiukeYouxiCehuaGangQiuzhiJingyanFenxiang20212022Fix1/img/close.png
NiukeYouxiCehuaGangQiuzhiJingyanFenxiang20212022Fix1/img/fullscreen.png
NiukeYouxiCehuaGangQiuzhiJingyanFenxiang20212022Fix1/img/loader.gif
NiukeYouxiCehuaGangQiuzhiJingyanFenxiang20212022Fix1/img/menu-icon.png
NiukeYouxiCehuaGangQiuzhiJingyanFenxiang20212022Fix1/img/save.png
NiukeYouxiCehuaGangQiuzhiJingyanFenxiang20212022Fix1/img/saved.png
NiukeYouxiCehuaGangQiuzhiJingyanFenxiang20212022Fix1/img/settings-s.png
NiukeYouxiCehuaGangQiuzhiJingyanFenxiang20212022Fix1/img/settings.png
niuke_youxi_cehua_gang_qiuzhi_jingyan_fenxiang_2021_2022_fix1-2025.3.25.0.dist-info/METADATA
niuke_youxi_cehua_gang_qiuzhi_jingyan_fenxiang_2021_2022_fix1-2025.3.25.0.dist-info/WHEEL
niuke_youxi_cehua_gang_qiuzhi_jingyan_fenxiang_2021_2022_fix1-2025.3.25.0.dist-info/entry_points.txt
niuke_youxi_cehua_gang_qiuzhi_jingyan_fenxiang_2021_2022_fix1-2025.3.25.0.dist-info/top_level.txt
niuke_youxi_cehua_gang_qiuzhi_jingyan_fenxiang_2021_2022_fix1-2025.3.25.0.dist-info/RECORD
